jupyter_up/__init__.py
jupyter_up/_version.py
jupyter_up/handlers.py
jupyter_up/tests/__init__.py
jupyter_up/tests/test_handlers.py
jupyter_up-0.0.3.data/data/etc/jupyter/jupyter_notebook_config.d/jupyter_up.json
jupyter_up-0.0.3.data/data/etc/jupyter/jupyter_server_config.d/jupyter_up.json
jupyter_up-0.0.3.data/data/share/jupyter/labextensions/@datalayer/jupyter-up/build_log.json
jupyter_up-0.0.3.data/data/share/jupyter/labextensions/@datalayer/jupyter-up/package.json
jupyter_up-0.0.3.data/data/share/jupyter/labextensions/@datalayer/jupyter-up/schemas/@datalayer/jupyter-up/package.json.orig
jupyter_up-0.0.3.data/data/share/jupyter/labextensions/@datalayer/jupyter-up/schemas/@datalayer/jupyter-up/plugin.json
jupyter_up-0.0.3.data/data/share/jupyter/labextensions/@datalayer/jupyter-up/static/lib_index_js.b0c2aee67df753a77a86.js
jupyter_up-0.0.3.data/data/share/jupyter/labextensions/@datalayer/jupyter-up/static/lib_index_js.b0c2aee67df753a77a86.js.map
jupyter_up-0.0.3.data/data/share/jupyter/labextensions/@datalayer/jupyter-up/static/node_modules_object-assign_index_js.e5e7a5a6bb477d18429b.js
jupyter_up-0.0.3.data/data/share/jupyter/labextensions/@datalayer/jupyter-up/static/node_modules_object-assign_index_js.e5e7a5a6bb477d18429b.js.map
jupyter_up-0.0.3.data/data/share/jupyter/labextensions/@datalayer/jupyter-up/static/remoteEntry.a8493cec60f054480453.js
jupyter_up-0.0.3.data/data/share/jupyter/labextensions/@datalayer/jupyter-up/static/remoteEntry.a8493cec60f054480453.js.map
jupyter_up-0.0.3.data/data/share/jupyter/labextensions/@datalayer/jupyter-up/static/style.js
jupyter_up-0.0.3.data/data/share/jupyter/labextensions/@datalayer/jupyter-up/static/style_index_js.6b702c847f7d6cac6396.js
jupyter_up-0.0.3.data/data/share/jupyter/labextensions/@datalayer/jupyter-up/static/style_index_js.6b702c847f7d6cac6396.js.map
jupyter_up-0.0.3.dist-info/METADATA
jupyter_up-0.0.3.dist-info/WHEEL
jupyter_up-0.0.3.dist-info/licenses/LICENSE
jupyter_up-0.0.3.dist-info/RECORD
